my_pypi_package_sample/__init__.py
my_pypi_package_sample/my_function.py
my_pypi_package_sample-0.1.2.dist-info/entry_points.txt
my_pypi_package_sample-0.1.2.dist-info/WHEEL
my_pypi_package_sample-0.1.2.dist-info/METADATA
my_pypi_package_sample-0.1.2.dist-info/RECORD
