Metadata-Version: 2.1
Name: my-pypi-package-sample
Version: 0.1.2
Summary: Print hello
Home-page: https://yahoo.com
License: MIT
Keywords: hello,xxx
Author: Hojung
Author-email: hojung_yun@yahoo.co.kr
Requires-Python: >=3.9,<4.0
Classifier: Environment :: Console
Classifier: Framework :: FastAPI
Classifier: License :: OSI Approved :: MIT License
Classifier: Operating System :: OS Independent
Classifier: Programming Language :: Python :: 3
Classifier: Programming Language :: Python :: 3.9
Classifier: Topic :: Software Development :: Documentation
Classifier: Topic :: Software Development :: Libraries :: Python Modules
Classifier: Topic :: Software Development :: Quality Assurance
Project-URL: Repository, https://yahoo.com
